codeinsight_sdk/__init__.py
codeinsight_sdk/client.py
codeinsight_sdk/exceptions.py
codeinsight_sdk/experimental.py
codeinsight_sdk/handler.py
codeinsight_sdk/handlers/__init__.py
codeinsight_sdk/handlers/inventory.py
codeinsight_sdk/handlers/project.py
codeinsight_sdk/handlers/report.py
codeinsight_sdk/models.py
codeinsight_sdk-0.0.14.dist-info/LICENSE
codeinsight_sdk-0.0.14.dist-info/METADATA
codeinsight_sdk-0.0.14.dist-info/WHEEL
codeinsight_sdk-0.0.14.dist-info/RECORD
