Metadata-Version: 2.1
Name: codeinsight-sdk
Version: 0.0.14
Summary: A Python client for the Revenera Code Insight
Home-page: https://github.com/zkarpinski/codeinsight-sdk-python
License: Apache-2.0
Keywords: revenera,api,flexera,code insight,sdk
Author: Zachary Karpinski
Author-email: 1206496+zkarpinski@users.noreply.github.com
Requires-Python: >=3.9,<4.0
Classifier: License :: OSI Approved :: Apache Software License
Classifier: Programming Language :: Python :: 3
Classifier: Programming Language :: Python :: 3.9
Classifier: Programming Language :: Python :: 3.10
Classifier: Programming Language :: Python :: 3.11
Requires-Dist: dataclasses-json (>=0.6.3,<0.7.0)
Requires-Dist: requests (>=2.31.0,<3.0.0)
Project-URL: Repository, https://github.com/zkarpinski/codeinsight-sdk-python
